odoo/addons/stock_product_template_tags/README.rst
odoo/addons/stock_product_template_tags/__init__.py
odoo/addons/stock_product_template_tags/__manifest__.py
odoo/addons/stock_product_template_tags/i18n/it.po
odoo/addons/stock_product_template_tags/i18n/stock_product_template_tags.pot
odoo/addons/stock_product_template_tags/readme/CONTRIBUTORS.md
odoo/addons/stock_product_template_tags/readme/DESCRIPTION.md
odoo/addons/stock_product_template_tags/static/description/icon.png
odoo/addons/stock_product_template_tags/static/description/index.html
odoo/addons/stock_product_template_tags/views/product_template_tag.xml
odoo_addon_stock_product_template_tags-17.0.1.0.0.2.dist-info/METADATA
odoo_addon_stock_product_template_tags-17.0.1.0.0.2.dist-info/WHEEL
odoo_addon_stock_product_template_tags-17.0.1.0.0.2.dist-info/top_level.txt
odoo_addon_stock_product_template_tags-17.0.1.0.0.2.dist-info/RECORD
